oec.py
oec-0.3.0.dist-info/LICENSE
oec-0.3.0.dist-info/METADATA
oec-0.3.0.dist-info/WHEEL
oec-0.3.0.dist-info/top_level.txt
oec-0.3.0.dist-info/RECORD
