Metadata-Version: 2.1
Name: oec
Version: 0.3.0
Summary: API Wrapper for The Observatory for Economic Complexity
Home-page: https://github.com/yahiaali/oec
Author: Yahia Ali
Author-email: yahiaali@me.com
License: MIT
Platform: UNKNOWN
Classifier: Development Status :: 5 - Production/Stable
Classifier: Intended Audience :: Science/Research
Classifier: Topic :: Software Development :: Build Tools
Classifier: License :: OSI Approved :: MIT License
Classifier: Programming Language :: Python :: 3 :: Only
Requires-Python: >=3
Requires-Dist: requests
